[
  {
    "asset": "^CNXENERGY",
    "mean_arch_volatility_forecast": 0.010695258923594833,
    "mean_custom_volatility_forecast": 0.0106413513555716,
    "mean_vol_forecast_gap": -5.3907568023233224e-05,
    "mean_vol_forecast_ratio": 0.995086616345471,
    "mean_arch_persistence": 0.7979624303448107,
    "mean_custom_persistence": 0.8894954479273396,
    "mean_persistence_gap": 0.09153301758252887,
    "mean_arch_std_resid_sq_lag1_acf": 0.031942594279674615,
    "mean_custom_std_resid_sq_lag1_acf": 0.06809943403106258,
    "mean_std_resid_sq_acf_gap": 0.036156839751387976,
    "mean_alpha_gap": 0.01599009498324198,
    "mean_gamma_gap": -0.08419818612374286,
    "mean_beta_gap": 0.11764201566115831,
    "mean_nu_gap": -0.36933260687477126,
    "arch_fallback_rate": 0.0,
    "custom_fallback_rate": 0.0,
    "arch_convergence_rate": 1.0,
    "custom_convergence_rate": 1.0
  },
  {
    "asset": "^CNXIT",
    "mean_arch_volatility_forecast": 0.010567543415189487,
    "mean_custom_volatility_forecast": 0.010550237672037112,
    "mean_vol_forecast_gap": -1.730574315237495e-05,
    "mean_vol_forecast_ratio": 0.9978608173340914,
    "mean_arch_persistence": 0.9659547078130216,
    "mean_custom_persistence": 0.9529858103976593,
    "mean_persistence_gap": -0.012968897415362337,
    "mean_arch_std_resid_sq_lag1_acf": 0.015359300460495707,
    "mean_custom_std_resid_sq_lag1_acf": 0.013889946114913976,
    "mean_std_resid_sq_acf_gap": -0.001469354345581731,
    "mean_alpha_gap": 1.5025965791708081e-05,
    "mean_gamma_gap": 0.008351353910889306,
    "mean_beta_gap": -0.017159600336598694,
    "mean_nu_gap": 0.5634658640263642,
    "arch_fallback_rate": 0.0,
    "custom_fallback_rate": 0.0,
    "arch_convergence_rate": 1.0,
    "custom_convergence_rate": 1.0
  },
  {
    "asset": "^CNXPHARMA",
    "mean_arch_volatility_forecast": 0.008302249849214176,
    "mean_custom_volatility_forecast": 0.008500336476456226,
    "mean_vol_forecast_gap": 0.00019808662724205077,
    "mean_vol_forecast_ratio": 1.023974652385767,
    "mean_arch_persistence": 0.8736610237469402,
    "mean_custom_persistence": 0.8764625783201773,
    "mean_persistence_gap": 0.002801554573237004,
    "mean_arch_std_resid_sq_lag1_acf": -0.005901994784797395,
    "mean_custom_std_resid_sq_lag1_acf": -0.010486079417025274,
    "mean_std_resid_sq_acf_gap": -0.004584084632227879,
    "mean_alpha_gap": 0.004024460973842732,
    "mean_gamma_gap": 0.01621800589565339,
    "mean_beta_gap": -0.009331909348432421,
    "mean_nu_gap": -4.865774079402124,
    "arch_fallback_rate": 0.0,
    "custom_fallback_rate": 0.0,
    "arch_convergence_rate": 1.0,
    "custom_convergence_rate": 1.0
  },
  {
    "asset": "^NSEBANK",
    "mean_arch_volatility_forecast": 0.008318968205787081,
    "mean_custom_volatility_forecast": 0.00819237089866229,
    "mean_vol_forecast_gap": -0.00012659730712479168,
    "mean_vol_forecast_ratio": 0.9857092451646345,
    "mean_arch_persistence": 0.9720183427718878,
    "mean_custom_persistence": 0.9727992838729066,
    "mean_persistence_gap": 0.0007809411010187423,
    "mean_arch_std_resid_sq_lag1_acf": 0.08789746774237359,
    "mean_custom_std_resid_sq_lag1_acf": 0.08801365599657208,
    "mean_std_resid_sq_acf_gap": 0.0001161882541985016,
    "mean_alpha_gap": 0.005954127857712974,
    "mean_gamma_gap": -0.011847398062986307,
    "mean_beta_gap": 0.0007505122747989192,
    "mean_nu_gap": 0.5951911971133441,
    "arch_fallback_rate": 0.0,
    "custom_fallback_rate": 0.0,
    "arch_convergence_rate": 1.0,
    "custom_convergence_rate": 1.0
  },
  {
    "asset": "^NSEI",
    "mean_arch_volatility_forecast": 0.0064456971982547765,
    "mean_custom_volatility_forecast": 0.006817260671212172,
    "mean_vol_forecast_gap": 0.00037156347295739557,
    "mean_vol_forecast_ratio": 1.0542319340430852,
    "mean_arch_persistence": 0.9736368658047938,
    "mean_custom_persistence": 0.9625729057285669,
    "mean_persistence_gap": -0.011063960076226838,
    "mean_arch_std_resid_sq_lag1_acf": 0.06719752409109885,
    "mean_custom_std_resid_sq_lag1_acf": 0.05449497669818,
    "mean_std_resid_sq_acf_gap": -0.01270254739291885,
    "mean_alpha_gap": -1.0473505303104404e-05,
    "mean_gamma_gap": 0.04338721152506096,
    "mean_beta_gap": -0.032747092333454214,
    "mean_nu_gap": -7.360300553062667,
    "arch_fallback_rate": 0.0,
    "custom_fallback_rate": 0.0,
    "arch_convergence_rate": 1.0,
    "custom_convergence_rate": 1.0
  }
]